fastcrop/__init__.py
fastcrop/__main__.py
fastcrop/gui.py
fastcrop-0.1.0.dist-info/licenses/LICENSE
fastcrop-0.1.0.dist-info/METADATA
fastcrop-0.1.0.dist-info/WHEEL
fastcrop-0.1.0.dist-info/entry_points.txt
fastcrop-0.1.0.dist-info/top_level.txt
fastcrop-0.1.0.dist-info/RECORD
