Metadata-Version: 2.4
Name: fastcrop
Version: 0.1.0
Summary: A minimal GUI app for image cropping
Requires-Python: >=3.14
License-File: LICENSE
Dynamic: license-file
